Scrapelytix/__init__.py
Scrapelytix/extraction.py
Scrapelytix/filter.py
Scrapelytix/plot.py
Scrapelytix-0.0.2.dist-info/METADATA
Scrapelytix-0.0.2.dist-info/WHEEL
Scrapelytix-0.0.2.dist-info/top_level.txt
Scrapelytix-0.0.2.dist-info/RECORD
