Metadata-Version: 2.1
Name: Scrapelytix
Version: 0.0.2
Summary: A package to allow analyzing soccer event data easily
Author: Soham Basu, Debrup Mitra
Author-email: basusoham034@gmail.com, 30debrup@gmail.com
License: Unlicensed
Keywords: python,soccer,soccer analysis,passing network
Classifier: Development Status :: 3 - Alpha
Classifier: Intended Audience :: Developers
Classifier: Operating System :: OS Independent
Classifier: Programming Language :: Python :: 3.8
Classifier: Programming Language :: Python :: 3.9
Classifier: Programming Language :: Python :: 3.10
Classifier: Programming Language :: Python :: 3.11
Requires-Python: >=3.8,<=3.12.1
